odoo/addons/web_widget_domain_editor_dialog/README.rst
odoo/addons/web_widget_domain_editor_dialog/__init__.py
odoo/addons/web_widget_domain_editor_dialog/__manifest__.py
odoo/addons/web_widget_domain_editor_dialog/i18n/es.po
odoo/addons/web_widget_domain_editor_dialog/i18n/web_widget_domain_editor_dialog.pot
odoo/addons/web_widget_domain_editor_dialog/readme/CONTRIBUTORS.rst
odoo/addons/web_widget_domain_editor_dialog/readme/DESCRIPTION.rst
odoo/addons/web_widget_domain_editor_dialog/readme/USAGE.rst
odoo/addons/web_widget_domain_editor_dialog/static/description/icon.png
odoo/addons/web_widget_domain_editor_dialog/static/description/index.html
odoo/addons/web_widget_domain_editor_dialog/static/src/img/behaviour.gif
odoo/addons/web_widget_domain_editor_dialog/static/src/js/basic_fields.js
odoo/addons/web_widget_domain_editor_dialog/static/src/js/widget_domain_editor_dialog.js
odoo/addons/web_widget_domain_editor_dialog/views/templates.xml
odoo11_addon_web_widget_domain_editor_dialog-11.0.1.0.1.dist-info/METADATA
odoo11_addon_web_widget_domain_editor_dialog-11.0.1.0.1.dist-info/WHEEL
odoo11_addon_web_widget_domain_editor_dialog-11.0.1.0.1.dist-info/top_level.txt
odoo11_addon_web_widget_domain_editor_dialog-11.0.1.0.1.dist-info/RECORD
